Workbook

Sheet Start Here
A1: Your 6-Jar Money Tracker
A3: How it works (read once, then you're set):
A5: 1. JARS tab — your six jars and their percentages. The blue numbers are yours to change.
A6: They must add up to 100% (there's a checker that tells you if they don't).
A8: 2. INCOME tab — add one row every time you get paid (net / take-home amount).
A10: 3. EXPENSES tab — add one row every time you spend. Pick which jar it came from
A11: from the dropdown. That's the only tab you'll touch day to day.
A13: 4. DASHBOARD tab — shows, per jar: how much you allocated, how much you've spent,
A14: and what's left. It updates by itself.
A16: THE ONE RULE THAT KEEPS THIS HONEST:
A17: Log every purchase ONCE, when it happens — whether you paid by card or cash.
A18: When your credit-card BILL arrives, do NOT log the payment as an expense.
... A28: Delete the example rows in Income and Expenses before you start for real.

Sheet Jars
A1: Your Jars
A2: Change the blue percentages to fit your life. They must total 100%.
A4: Jar | B4: Percentage | C4: Type | D4: Notes
A5: Financial Freedom | B5: 0.1 | C5: Accumulate | D5: Invest only. Never spend the principal — let it grow.
A6: Long-Term Savings | B6: 0.1 | C6: Accumulate | D6: Big future purchases, reserves, emergencies.
A7: Education | B7: 0.1 | C7: Spend | D7: Courses, books, coaching, skills.
A8: Play | B8: 0.1 | C8: Spend | D8: Guilt-free fun. Empty it regularly — that's the point.
A9: Give | B9: 0.1 | C9: Accumulate | D9: Charity / causes. Accumulates until you donate.
A10: Necessities | B10: 0.5 | C10: Spend | D10: Rent, food, bills, transport. Adjust up if 50% is tight.
A11: Total | B11: =SUM(B5:B10) -> 1
A12: =IF(ABS(SUM(B5:B10)-1)<0.0001,"OK — your jars total 100%","FIX THIS: percentages must total 100%") -> OK — your jars total 100%

Sheet Income
A1: Income (your take-home pay)
A2: Add a row each payday. Delete the example rows below before starting for real.
A4: Date | B4: Source | C4: Net Amount
A5: 2026-01-15 | B5: Paycheck (EXAMPLE) | C5: 2000
A6: 2026-01-31 | B6: Paycheck (EXAMPLE) | C6: 2000

Sheet Expenses
A1: Expenses (log every purchase, once)
A2: Pick the jar from the dropdown. Do NOT log credit-card BILL payments here.
A4: Date | B4: Jar | C4: Amount | D4: Note | E4: Paid With
A5: 2026-01-16 | B5: Necessities | C5: 1200 | D5: Rent (EXAMPLE) | E5: Cash/Debit
A6: 2026-01-17 | B6: Necessities | C6: 150 | D6: Groceries (EXAMPLE) | E6: Credit Card
A7: 2026-01-18 | B7: Play | C7: 60 | D7: Dinner out (EXAMPLE) | E7: Credit Card
A8: 2026-01-20 | B8: Education | C8: 80 | D8: Online course (EXAMPLE) | E8: Credit Card
A9: 2026-01-22 | B9: Give | C9: 50 | D9: Donation (EXAMPLE) | E9: Cash/Debit

Sheet Dashboard
A1: 6-Jar Dashboard
A3: Total Net Income | B3: =SUM(Income!C5:C1000) -> 4000
A5: Jar | B5: Type | C5: Allocated | D5: Spent / Used | E5: Balance Left | F5: % Used
A6: =Jars!A5 -> Financial Freedom | B6: =Jars!C5 -> Accumulate | C6: =$B$3*Jars!B5 -> 400 | D6: =SUMIF(Expenses!$B$5:$B$1000,A6,Expenses!$C$5:$C$1000) -> 0 | E6: =C6-D6 -> 400 | F6: =IF(C6=0,0,D6/C6) -> 0
A7: =Jars!A6 -> Long-Term Savings | B7: =Jars!C6 -> Accumulate | C7: =$B$3*Jars!B6 -> 400 | D7: =SUMIF(Expenses!$B$5:$B$1000,A7,Expenses!$C$5:$C$1000) -> 0 | E7: =C7-D7 -> 400 | F7: =IF(C7=0,0,D7/C7) -> 0
A8: =Jars!A7 -> Education | B8: =Jars!C7 -> Spend | C8: =$B$3*Jars!B7 -> 400 | D8: =SUMIF(Expenses!$B$5:$B$1000,A8,Expenses!$C$5:$C$1000) -> 80 | E8: =C8-D8 -> 320 | F8: =IF(C8=0,0,D8/C8) -> 0.2
A9: =Jars!A8 -> Play | B9: =Jars!C8 -> Spend | C9: =$B$3*Jars!B8 -> 400 | D9: =SUMIF(Expenses!$B$5:$B$1000,A9,Expenses!$C$5:$C$1000) -> 60 | E9: =C9-D9 -> 340 | F9: =IF(C9=0,0,D9/C9) -> 0.15
A10: =Jars!A9 -> Give | B10: =Jars!C9 -> Accumulate | C10: =$B$3*Jars!B9 -> 400 | D10: =SUMIF(Expenses!$B$5:$B$1000,A10,Expenses!$C$5:$C$1000) -> 50 | E10: =C10-D10 -> 350 | F10: =IF(C10=0,0,D10/C10) -> 0.125
A11: =Jars!A10 -> Necessities | B11: =Jars!C10 -> Spend | C11: =$B$3*Jars!B10 -> 2000 | D11: =SUMIF(Expenses!$B$5:$B$1000,A11,Expenses!$C$5:$C$1000) -> 1350 | E11: =C11-D11 -> 650 | F11: =IF(C11=0,0,D11/C11) -> 0.675
A12: Total | C12: =SUM(C6:C11) -> 4000 | D12: =SUM(D6:D11) -> 1540 | E12: =SUM(E6:E11) -> 2460
A14: Reminder: 'Balance Left' on Financial Freedom / Give / Long-Term Savings is money ACCUMULATING, not money to burn through.
